<annotation verified="yes">
    <folder>Annotation</folder>
    <filename>910.jpg</filename>
    <path>tento-PascalVOC-export/Annotations/910.jpg</path>
    <source>
        <database>Unknown</database>
    </source>
    <size>
        <width>640</width>
        <height>469</height>
        <depth>3</depth>
    </size>
    <segmented>0</segmented>
    <object>
    <name>red</name>
    <pose>Unspecified</pose>
    <truncated>0</truncated>
    <difficult>0</difficult>
    <bndbox>
        <xmin>286.75418745408916</xmin>
        <ymin>27.08662910257431</ymin>
        <xmax>338.4054867317581</xmax>
        <ymax>84.26952445698294</ymax>
    </bndbox>
</object><object>
    <name>two_spots</name>
    <pose>Unspecified</pose>
    <truncated>0</truncated>
    <difficult>0</difficult>
    <bndbox>
        <xmin>407.60824444478453</xmin>
        <ymin>70.72620512202461</ymin>
        <xmax>456.2507364869001</xmax>
        <ymax>128.91230329217757</ymax>
    </bndbox>
</object><object>
    <name>two_spots</name>
    <pose>Unspecified</pose>
    <truncated>0</truncated>
    <difficult>0</difficult>
    <bndbox>
        <xmin>117.25760016221842</xmin>
        <ymin>95.80641902576792</ymin>
        <xmax>174.42509067397162</xmax>
        <ymax>146.4684530247979</ymax>
    </bndbox>
</object><object>
    <name>red</name>
    <pose>Unspecified</pose>
    <truncated>0</truncated>
    <difficult>0</difficult>
    <bndbox>
        <xmin>70.11949260834966</xmin>
        <ymin>80.75829068352193</ymin>
        <xmax>120.76788802338395</xmax>
        <ymax>140.95081361984822</ymax>
    </bndbox>
</object><object>
    <name>red</name>
    <pose>Unspecified</pose>
    <truncated>0</truncated>
    <difficult>0</difficult>
    <bndbox>
        <xmin>474.3036181592802</xmin>
        <ymin>319.5219480953114</ymin>
        <xmax>525.4534941999266</xmax>
        <ymax>379.71446146429537</ymax>
    </bndbox>
</object><object>
    <name>two_spots_mutant</name>
    <pose>Unspecified</pose>
    <truncated>0</truncated>
    <difficult>0</difficult>
    <bndbox>
        <xmin>540.9990683918952</xmin>
        <ymin>219.7026699698545</ymin>
        <xmax>591.1459831813173</xmax>
        <ymax>267.8566921458525</ymax>
    </bndbox>
</object><object>
    <name>red</name>
    <pose>Unspecified</pose>
    <truncated>0</truncated>
    <difficult>0</difficult>
    <bndbox>
        <xmin>443.2125462934623</xmin>
        <ymin>120.88664249685358</ymin>
        <xmax>482.82861662891776</xmax>
        <ymax>171.5486669285412</ymax>
    </bndbox>
</object><object>
    <name>two_spots</name>
    <pose>Unspecified</pose>
    <truncated>0</truncated>
    <difficult>0</difficult>
    <bndbox>
        <xmin>153.36338263650833</xmin>
        <ymin>201.14332698883217</ymin>
        <xmax>200.50147106084722</xmax>
        <ymax>257.32299082546945</ymax>
    </bndbox>
</object><object>
    <name>two_spots</name>
    <pose>Unspecified</pose>
    <truncated>0</truncated>
    <difficult>0</difficult>
    <bndbox>
        <xmin>200.50147106084722</xmin>
        <ymin>216.19145533107817</ymin>
        <xmax>265.1909987910137</xmax>
        <ymax>272.37113830240014</ymax>
    </bndbox>
</object><object>
    <name>two_spots</name>
    <pose>Unspecified</pose>
    <truncated>0</truncated>
    <difficult>0</difficult>
    <bndbox>
        <xmin>176.93243641344273</xmin>
        <ymin>97.31122803305558</ymin>
        <xmax>230.58961993450052</xmax>
        <ymax>159.00855997666955</ymax>
    </bndbox>
</object><object>
    <name>two_spots</name>
    <pose>Unspecified</pose>
    <truncated>0</truncated>
    <difficult>0</difficult>
    <bndbox>
        <xmin>17.465232079456417</xmin>
        <ymin>170.04385792125353</ymin>
        <xmax>65.10480112940745</xmax>
        <ymax>238.76364784444715</ymax>
    </bndbox>
</object><object>
    <name>red</name>
    <pose>Unspecified</pose>
    <truncated>0</truncated>
    <difficult>0</difficult>
    <bndbox>
        <xmin>67.11068537279628</xmin>
        <ymin>159.00855997666955</ymin>
        <xmax>112.74437017935848</xmax>
        <ymax>211.6770091745305</ymax>
    </bndbox>
</object><object>
    <name>red</name>
    <pose>Unspecified</pose>
    <truncated>0</truncated>
    <difficult>0</difficult>
    <bndbox>
        <xmin>27.494615037340843</xmin>
        <ymin>121.88983574525557</ymin>
        <xmax>85.66504767078845</xmax>
        <ymax>165.02781514050488</ymax>
    </bndbox>
</object><object>
    <name>two_spots</name>
    <pose>Unspecified</pose>
    <truncated>0</truncated>
    <difficult>0</difficult>
    <bndbox>
        <xmin>222.5661212200049</xmin>
        <ymin>73.73583270394228</ymin>
        <xmax>270.70715176603824</xmax>
        <ymax>134.9315584560129</ymax>
    </bndbox>
</object><object>
    <name>two_spots</name>
    <pose>Unspecified</pose>
    <truncated>0</truncated>
    <difficult>0</difficult>
    <bndbox>
        <xmin>273.2144975055093</xmin>
        <ymin>87.27914247155826</ymin>
        <xmax>322.8599507988492</xmax>
        <ymax>136.43636746330054</ymax>
    </bndbox>
</object><object>
    <name>two_spots</name>
    <pose>Unspecified</pose>
    <truncated>0</truncated>
    <difficult>0</difficult>
    <bndbox>
        <xmin>281.73949597514695</xmin>
        <ymin>130.9187280583509</ymin>
        <xmax>332.38787226065136</xmax>
        <ymax>188.10160427807483</ymax>
    </bndbox>
</object><object>
    <name>two_spots</name>
    <pose>Unspecified</pose>
    <truncated>0</truncated>
    <difficult>0</difficult>
    <bndbox>
        <xmin>227.07935120286484</xmin>
        <ymin>131.9219213067529</ymin>
        <xmax>277.7277274883693</xmax>
        <ymax>174.05668831891552</ymax>
    </bndbox>
</object><object>
    <name>two_spots</name>
    <pose>Unspecified</pose>
    <truncated>0</truncated>
    <difficult>0</difficult>
    <bndbox>
        <xmin>247.13811711863372</xmin>
        <ymin>265.8502673796791</ymin>
        <xmax>295.7806091607493</xmax>
        <ymax>308.98822764024374</ymax>
    </bndbox>
</object><object>
    <name>two_spots</name>
    <pose>Unspecified</pose>
    <truncated>0</truncated>
    <difficult>0</difficult>
    <bndbox>
        <xmin>496.86976807357985</xmin>
        <ymin>198.13368983957218</ymin>
        <xmax>550.0254518394956</xmax>
        <ymax>239.26524446864812</ymax>
    </bndbox>
</object><object>
    <name>two_spots</name>
    <pose>Unspecified</pose>
    <truncated>0</truncated>
    <difficult>0</difficult>
    <bndbox>
        <xmin>544.5093371235309</xmin>
        <ymin>169.04064553816687</ymin>
        <xmax>604.1841351156955</xmax>
        <ymax>214.68662718910582</ymax>
    </bndbox>
</object><object>
    <name>two_spots</name>
    <pose>Unspecified</pose>
    <truncated>0</truncated>
    <difficult>0</difficult>
    <bndbox>
        <xmin>420.1449731421401</xmin>
        <ymin>228.22994652406416</ymin>
        <xmax>482.82861662891776</xmax>
        <ymax>283.90801373650044</ymax>
    </bndbox>
</object><object>
    <name>two_spots</name>
    <pose>Unspecified</pose>
    <truncated>0</truncated>
    <difficult>0</difficult>
    <bndbox>
        <xmin>404.09793745408916</xmin>
        <ymin>283.40641711229944</ymin>
        <xmax>458.75808222637124</xmax>
        <ymax>339.08448432473574</ymax>
    </bndbox>
</object><object>
    <name>red</name>
    <pose>Unspecified</pose>
    <truncated>0</truncated>
    <difficult>0</difficult>
    <bndbox>
        <xmin>328.3761037738737</xmin>
        <ymin>347.6117800136301</ymin>
        <xmax>379.0244800593781</xmax>
        <ymax>391.2513368983957</ymax>
    </bndbox>
</object><object>
    <name>red</name>
    <pose>Unspecified</pose>
    <truncated>0</truncated>
    <difficult>0</difficult>
    <bndbox>
        <xmin>234.6013884212782</xmin>
        <ymin>308.48663101604274</ymin>
        <xmax>287.25564895017146</xmax>
        <ymax>366.67271961885336</ymax>
    </bndbox>
</object><object>
    <name>two_spots</name>
    <pose>Unspecified</pose>
    <truncated>0</truncated>
    <difficult>0</difficult>
    <bndbox>
        <xmin>305.8099921186337</xmin>
        <ymin>242.27486248322347</ymin>
        <xmax>355.9569069080559</xmax>
        <ymax>287.92086326884714</ymax>
    </bndbox>
</object><object>
    <name>red</name>
    <pose>Unspecified</pose>
    <truncated>0</truncated>
    <difficult>0</difficult>
    <bndbox>
        <xmin>381.5318257988492</xmin>
        <ymin>202.64813599611983</ymin>
        <xmax>424.156703369858</xmax>
        <ymax>263.8438426135058</ymax>
    </bndbox>
</object><object>
    <name>two_spots</name>
    <pose>Unspecified</pose>
    <truncated>0</truncated>
    <difficult>0</difficult>
    <bndbox>
        <xmin>369.998058352718</xmin>
        <ymin>125.90268527760225</ymin>
        <xmax>436.1919705711313</xmax>
        <ymax>179.5743277238652</ymax>
    </bndbox>
</object><object>
    <name>two_spots</name>
    <pose>Unspecified</pose>
    <truncated>0</truncated>
    <difficult>0</difficult>
    <bndbox>
        <xmin>42.538689474167484</xmin>
        <ymin>289.92728803502047</ymin>
        <xmax>106.72673657872184</xmax>
        <ymax>345.60535524745677</ymax>
    </bndbox>
</object><object>
    <name>two_spots</name>
    <pose>Unspecified</pose>
    <truncated>0</truncated>
    <difficult>0</difficult>
    <bndbox>
        <xmin>0.4152829640058766</xmin>
        <ymin>303.9721848594951</ymin>
        <xmax>43.5416315958619</xmax>
        <ymax>370.68556915120007</ymax>
    </bndbox>
</object><object>
    <name>two_spots</name>
    <pose>Unspecified</pose>
    <truncated>0</truncated>
    <difficult>0</difficult>
    <bndbox>
        <xmin>135.8119624602106</xmin>
        <ymin>317.0139267049371</ymin>
        <xmax>194.98531808582274</xmax>
        <ymax>363.16150498007704</ymax>
    </bndbox>
</object><object>
    <name>two_spots</name>
    <pose>Unspecified</pose>
    <truncated>0</truncated>
    <difficult>0</difficult>
    <bndbox>
        <xmin>106.72673657872186</xmin>
        <ymin>252.3069480447208</ymin>
        <xmax>166.90303432602843</xmax>
        <ymax>308.48663101604274</ymax>
    </bndbox>
</object><object>
    <name>two_spots</name>
    <pose>Unspecified</pose>
    <truncated>0</truncated>
    <difficult>0</difficult>
    <bndbox>
        <xmin>59.08716752877082</xmin>
        <ymin>233.2459893048128</ymin>
        <xmax>106.72673657872186</xmax>
        <ymax>284.40964863007076</ymax>
    </bndbox>
</object><object>
    <name>two_spots</name>
    <pose>Unspecified</pose>
    <truncated>0</truncated>
    <difficult>0</difficult>
    <bndbox>
        <xmin>98.70323786422625</xmin>
        <ymin>188.10160427807486</ymin>
        <xmax>153.8648441325906</xmax>
        <ymax>252.3069480447208</ymax>
    </bndbox>
</object><object>
    <name>two_spots_mutant</name>
    <pose>Unspecified</pose>
    <truncated>0</truncated>
    <difficult>0</difficult>
    <bndbox>
        <xmin>148.8501526536484</xmin>
        <ymin>140.44919786096256</ymin>
        <xmax>193.48089533851618</xmax>
        <ymax>194.62245606611117</ymax>
    </bndbox>
</object><object>
    <name>two_spots</name>
    <pose>Unspecified</pose>
    <truncated>0</truncated>
    <difficult>0</difficult>
    <bndbox>
        <xmin>252.15280859757593</xmin>
        <ymin>181.07915586583752</ymin>
        <xmax>306.311453614716</xmax>
        <ymax>222.21069136022882</ymax>
    </bndbox>
</object><object>
    <name>two_spots</name>
    <pose>Unspecified</pose>
    <truncated>0</truncated>
    <difficult>0</difficult>
    <bndbox>
        <xmin>485.83742386447113</xmin>
        <ymin>152.9893048128342</ymin>
        <xmax>542.5034146210824</xmax>
        <ymax>201.64492361303317</ymax>
    </bndbox>
</object><object>
    <name>two_spots</name>
    <pose>Unspecified</pose>
    <truncated>0</truncated>
    <difficult>0</difficult>
    <bndbox>
        <xmin>421.64935763038693</xmin>
        <ymin>166.03102752359155</ymin>
        <xmax>471.38099902056814</xmax>
        <ymax>224.71871275060317</ymax>
    </bndbox>
</object>
</annotation>
